CHANGELOG.md
LICENSE
MANIFEST.in
README.md
setup.cfg
setup.py
eic_aichat_connect/__init__.py
eic_aichat_connect.egg-info/PKG-INFO
eic_aichat_connect.egg-info/SOURCES.txt
eic_aichat_connect.egg-info/dependency_links.txt
eic_aichat_connect.egg-info/requires.txt
eic_aichat_connect.egg-info/top_level.txt
eic_aichat_connect.egg-info/zip-safe
eic_aichat_connect/build/AIChatConnectFactory.py
eic_aichat_connect/build/__init__.py
eic_aichat_connect/connectors/AnthropicModelConnector.py
eic_aichat_connect/connectors/DeepSeekModelConnector.py
eic_aichat_connect/connectors/IModelConnector.py
eic_aichat_connect/connectors/MockModelConnector.py
eic_aichat_connect/connectors/OpenAIModelConnector.py
eic_aichat_connect/connectors/PerplexityModelConnector.py
eic_aichat_connect/connectors/__init__.py
eic_aichat_connect/data/__init__.py
eic_aichat_connect/data/version1/ModelRequestV1.py
eic_aichat_connect/data/version1/ModelRequestV1Schema.py
eic_aichat_connect/data/version1/ModelResponseV1.py
eic_aichat_connect/data/version1/ModelResponseV1Schema.py
eic_aichat_connect/data/version1/ModelTypesV1.py
eic_aichat_connect/data/version1/__init__.py
eic_aichat_connect/operations/__init__.py
eic_aichat_connect/operations/version1/ModelConnectionOperationsV1.py
eic_aichat_connect/operations/version1/__init__.py
eic_aichat_connect/services/IModelConnectionService.py
eic_aichat_connect/services/ModelConnectionService.py
eic_aichat_connect/services/__init__.py
test/operations/__init__.py
test/operations/version1/__init__.py
test/operations/version1/test_ModelConnectionOperationsV1.py
test/services/__init__.py
test/services/test_ModelConnectionService.py